throttlekit/__init__.py
throttlekit/leaky_limiter.py
throttlekit/limiter.py
throttlekit-0.1.0.dist-info/WHEEL
throttlekit-0.1.0.dist-info/METADATA
throttlekit-0.1.0.dist-info/RECORD
