Metadata-Version: 2.4
Name: throttlekit
Version: 0.1.0
Summary: Fast asyncio-compatible token bucket rate limiter
Author: Roudrasekhar Majumder
Author-email: Roudrasekhar Majumder <roudra25@gmail.com>
License-Expression: MIT
Classifier: Programming Language :: Python :: 3
Classifier: Programming Language :: Python :: 3.9
Classifier: Programming Language :: Python :: 3.10
Classifier: Programming Language :: Python :: 3.11
Classifier: Programming Language :: Python :: 3.12
Classifier: License :: OSI Approved :: MIT License
Classifier: Operating System :: OS Independent
Classifier: Intended Audience :: Developers
Classifier: Topic :: Software Development :: Libraries
Requires-Dist: typing-extensions>=4.0.0 ; python_full_version < '3.10'
Requires-Python: >=3.9
